{"note":"This file is an internal implementation detail to speed up HTML report generation. Its format can change at any time. You might be looking for the JSON report: https://coverage.rtfd.io/cmd.html#cmd-json","format":5,"version":"7.8.0","globals":"c2f19238a374df94e0c2706b2456905f","files":{"z_2e3eaab626e4e78a_auth_controller_py":{"hash":"178c627ab98e409d48689954428152a5","index":{"url":"z_2e3eaab626e4e78a_auth_controller_py.html","file":"app/controllers/auth_controller.py","description":"","nums":{"precision":0,"n_files":1,"n_statements":27,"n_excluded":0,"n_missing":3,"n_branches":0,"n_partial_branches":0,"n_missing_branches":0}}},"z_2e3eaab626e4e78a_event_controller_py":{"hash":"4081ee5a041a3615d9d7a69d7187c22a","index":{"url":"z_2e3eaab626e4e78a_event_controller_py.html","file":"app/controllers/event_controller.py","description":"","nums":{"precision":0,"n_files":1,"n_statements":17,"n_excluded":0,"n_missing":2,"n_branches":0,"n_partial_branches":0,"n_missing_branches":0}}},"z_2e3eaab626e4e78a_users_controller_py":{"hash":"3a29c7b5f3c3caa472f3fe6837827244","index":{"url":"z_2e3eaab626e4e78a_users_controller_py.html","file":"app/controllers/users_controller.py","description":"","nums":{"precision":0,"n_files":1,"n_statements":28,"n_excluded":0,"n_missing":0,"n_branches":0,"n_partial_branches":0,"n_missing_branches":0}}},"z_2e3eaab626e4e78a_world_controller_py":{"hash":"2668da92d8e9994afa194abed3b90520","index":{"url":"z_2e3eaab626e4e78a_world_controller_py.html","file":"app/controllers/world_controller.py","description":"","nums":{"precision":0,"n_files":1,"n_statements":72,"n_excluded":0,"n_missing":18,"n_branches":0,"n_partial_branches":0,"n_missing_branches":0}}},"z_8f7e1016f2d37417_exceptions_py":{"hash":"51191cfc482f7c54c41b6bdb70ff1547","index":{"url":"z_8f7e1016f2d37417_exceptions_py.html","file":"app/core/exceptions.py","description":"","nums":{"precision":0,"n_files":1,"n_statements":31,"n_excluded":0,"n_missing":7,"n_branches":0,"n_partial_branches":0,"n_missing_branches":0}}},"z_8f7e1016f2d37417_security_py":{"hash":"c65f585b114e407f7e7659683b65b722","index":{"url":"z_8f7e1016f2d37417_security_py.html","file":"app/core/security.py","description":"","nums":{"precision":0,"n_files":1,"n_statements":34,"n_excluded":0,"n_missing":12,"n_branches":8,"n_partial_branches":1,"n_missing_branches":5}}},"z_395c4f306d1419cf_models_py":{"hash":"94925db7a224409830661bdf992c759d","index":{"url":"z_395c4f306d1419cf_models_py.html","file":"app/db/models.py","description":"","nums":{"precision":0,"n_files":1,"n_statements":144,"n_excluded":0,"n_missing":0,"n_branches":0,"n_partial_branches":0,"n_missing_branches":0}}},"z_395c4f306d1419cf_supabaseDB_py":{"hash":"cdcbb8a52ff6e38adfcf953ae5c9f52c","index":{"url":"z_395c4f306d1419cf_supabaseDB_py.html","file":"app/db/supabaseDB.py","description":"","nums":{"precision":0,"n_files":1,"n_statements":20,"n_excluded":0,"n_missing":4,"n_branches":0,"n_partial_branches":0,"n_missing_branches":0}}},"z_5f5a17c013354698_gateway_py":{"hash":"931333e409ab37f85e53b4b683970700","index":{"url":"z_5f5a17c013354698_gateway_py.html","file":"app/gateway.py","description":"","nums":{"precision":0,"n_files":1,"n_statements":16,"n_excluded":0,"n_missing":1,"n_branches":0,"n_partial_branches":0,"n_missing_branches":0}}},"z_c318f3fa19a49f69_change_world_description_py":{"hash":"c9cdb5134e7041540ead44174886eb34","index":{"url":"z_c318f3fa19a49f69_change_world_description_py.html","file":"app/services/change_world_description.py","description":"","nums":{"precision":0,"n_files":1,"n_statements":13,"n_excluded":0,"n_missing":10,"n_branches":2,"n_partial_branches":0,"n_missing_branches":2}}},"z_c318f3fa19a49f69_change_world_name_py":{"hash":"0be4d96d20783c60b5d2b2e5a0c6600b","index":{"url":"z_c318f3fa19a49f69_change_world_name_py.html","file":"app/services/change_world_name.py","description":"","nums":{"precision":0,"n_files":1,"n_statements":16,"n_excluded":0,"n_missing":13,"n_branches":4,"n_partial_branches":0,"n_missing_branches":4}}},"z_c318f3fa19a49f69_change_world_time_py":{"hash":"72c474317aecefefaf36a5d9f8a5c299","index":{"url":"z_c318f3fa19a49f69_change_world_time_py.html","file":"app/services/change_world_time.py","description":"","nums":{"precision":0,"n_files":1,"n_statements":15,"n_excluded":0,"n_missing":11,"n_branches":2,"n_partial_branches":0,"n_missing_branches":2}}},"z_c318f3fa19a49f69_create_world_py":{"hash":"491410720ad2e4065a75af06b4e4233f","index":{"url":"z_c318f3fa19a49f69_create_world_py.html","file":"app/services/create_world.py","description":"","nums":{"precision":0,"n_files":1,"n_statements":17,"n_excluded":0,"n_missing":14,"n_branches":2,"n_partial_branches":0,"n_missing_branches":2}}},"z_c318f3fa19a49f69_create_world_event_py":{"hash":"5139e6bd700abd4baba0d833e00b2a23","index":{"url":"z_c318f3fa19a49f69_create_world_event_py.html","file":"app/services/create_world_event.py","description":"","nums":{"precision":0,"n_files":1,"n_statements":14,"n_excluded":0,"n_missing":10,"n_branches":2,"n_partial_branches":0,"n_missing_branches":2}}},"z_c318f3fa19a49f69_create_world_time_py":{"hash":"892bd82c763e0c105b12a257cc3f6e3c","index":{"url":"z_c318f3fa19a49f69_create_world_time_py.html","file":"app/services/create_world_time.py","description":"","nums":{"precision":0,"n_files":1,"n_statements":12,"n_excluded":0,"n_missing":8,"n_branches":0,"n_partial_branches":0,"n_missing_branches":0}}},"z_c318f3fa19a49f69_delete_world_py":{"hash":"47762ed3e6a6935ca2522ca3900aee38","index":{"url":"z_c318f3fa19a49f69_delete_world_py.html","file":"app/services/delete_world.py","description":"","nums":{"precision":0,"n_files":1,"n_statements":13,"n_excluded":0,"n_missing":10,"n_branches":2,"n_partial_branches":0,"n_missing_branches":2}}},"z_c318f3fa19a49f69_delete_world_time_py":{"hash":"10cbcc5064b29feb8c2b6f9fe4317b2e","index":{"url":"z_c318f3fa19a49f69_delete_world_time_py.html","file":"app/services/delete_world_time.py","description":"","nums":{"precision":0,"n_files":1,"n_statements":13,"n_excluded":0,"n_missing":10,"n_branches":2,"n_partial_branches":0,"n_missing_branches":2}}},"z_c318f3fa19a49f69_events_py":{"hash":"341a13a6063f030fa9621333a7d97067","index":{"url":"z_c318f3fa19a49f69_events_py.html","file":"app/services/events.py","description":"","nums":{"precision":0,"n_files":1,"n_statements":10,"n_excluded":0,"n_missing":2,"n_branches":0,"n_partial_branches":0,"n_missing_branches":0}}},"z_c318f3fa19a49f69_login_py":{"hash":"4e4aa66c61bc160af81c7f58725f33b4","index":{"url":"z_c318f3fa19a49f69_login_py.html","file":"app/services/login.py","description":"","nums":{"precision":0,"n_files":1,"n_statements":21,"n_excluded":0,"n_missing":3,"n_branches":4,"n_partial_branches":2,"n_missing_branches":2}}},"z_c318f3fa19a49f69_notifications_py":{"hash":"0b436225ded64603a304fa3189816f7b","index":{"url":"z_c318f3fa19a49f69_notifications_py.html","file":"app/services/notifications.py","description":"","nums":{"precision":0,"n_files":1,"n_statements":14,"n_excluded":0,"n_missing":2,"n_branches":0,"n_partial_branches":0,"n_missing_branches":0}}},"z_c318f3fa19a49f69_register_py":{"hash":"06bcde00f1005962ffc370d5956dddf5","index":{"url":"z_c318f3fa19a49f69_register_py.html","file":"app/services/register.py","description":"","nums":{"precision":0,"n_files":1,"n_statements":21,"n_excluded":0,"n_missing":4,"n_branches":6,"n_partial_branches":2,"n_missing_branches":2}}},"z_c318f3fa19a49f69_search_world_id_py":{"hash":"9c7082c622382b8d42e64125d3313a26","index":{"url":"z_c318f3fa19a49f69_search_world_id_py.html","file":"app/services/search_world_id.py","description":"","nums":{"precision":0,"n_files":1,"n_statements":8,"n_excluded":0,"n_missing":5,"n_branches":0,"n_partial_branches":0,"n_missing_branches":0}}},"z_c318f3fa19a49f69_update_world_settings_py":{"hash":"0063e0b73f5d5bc21d3f948c193dee2c","index":{"url":"z_c318f3fa19a49f69_update_world_settings_py.html","file":"app/services/update_world_settings.py","description":"","nums":{"precision":0,"n_files":1,"n_statements":21,"n_excluded":0,"n_missing":17,"n_branches":2,"n_partial_branches":0,"n_missing_branches":2}}},"z_c318f3fa19a49f69_user_py":{"hash":"2e67025e19c6d1f5570d1e3941c9063c","index":{"url":"z_c318f3fa19a49f69_user_py.html","file":"app/services/user.py","description":"","nums":{"precision":0,"n_files":1,"n_statements":18,"n_excluded":0,"n_missing":1,"n_branches":2,"n_partial_branches":0,"n_missing_branches":0}}}}}